<NotepadPlus>
    <InternalCommands />
    <Macros>
        <Macro name="Trim Trailing and save" Ctrl="no" Alt="yes" Shift="yes" Key="83">
            <Action type="2" message="0" wParam="42024" lParam="0" sParam="" />
            <Action type="2" message="0" wParam="41006" lParam="0" sParam="" />
        </Macro>
        <Macro name="SelectInBetween" Ctrl="yes" Alt="yes" Shift="no" Key="81">
            <Action type="3" message="1700" wParam="0" lParam="0" sParam="" />
            <Action type="3" message="1601" wParam="0" lParam="0" sParam="(?&lt;=\*##s)[^\n]*\n\K[\s\S]*(?=\*##e)" />
            <Action type="3" message="1625" wParam="0" lParam="2" sParam="" />
            <Action type="3" message="1702" wParam="0" lParam="768" sParam="" />
            <Action type="3" message="1701" wParam="0" lParam="1723" sParam="" />
        </Macro>
        <Macro name="StartingPoint" Ctrl="yes" Alt="yes" Shift="no" Key="90">
            <Action type="0" message="2453" wParam="0" lParam="0" sParam="" />
            <Action type="1" message="2170" wParam="0" lParam="0" sParam="*" />
            <Action type="1" message="2170" wParam="0" lParam="0" sParam="#" />
            <Action type="1" message="2170" wParam="0" lParam="0" sParam="#" />
            <Action type="1" message="2170" wParam="0" lParam="0" sParam="n" />
            <Action type="1" message="2170" wParam="0" lParam="0" sParam="n" />
            <Action type="1" message="2170" wParam="0" lParam="0" sParam="&#x000D;" />
            <Action type="1" message="2170" wParam="0" lParam="0" sParam="&#x000A;" />
            <Action type="0" message="2452" wParam="0" lParam="0" sParam="" />
            <Action type="0" message="2326" wParam="0" lParam="0" sParam="" />
            <Action type="3" message="1700" wParam="0" lParam="0" sParam="" />
            <Action type="3" message="1601" wParam="0" lParam="0" sParam="^(\*##s)[^\n]*" />
            <Action type="3" message="1625" wParam="0" lParam="2" sParam="" />
            <Action type="3" message="1602" wParam="0" lParam="0" sParam="" />
            <Action type="3" message="1702" wParam="0" lParam="256" sParam="" />
            <Action type="3" message="1701" wParam="0" lParam="1609" sParam="" />
            <Action type="3" message="1700" wParam="0" lParam="0" sParam="" />
            <Action type="3" message="1601" wParam="0" lParam="0" sParam="^(\*##nn)[^\n]*" />
            <Action type="3" message="1625" wParam="0" lParam="2" sParam="" />
            <Action type="3" message="1602" wParam="0" lParam="0" sParam="*##s" />
            <Action type="3" message="1702" wParam="0" lParam="256" sParam="" />
            <Action type="3" message="1701" wParam="0" lParam="1609" sParam="" />
        </Macro>
        <Macro name="EndingPoint" Ctrl="yes" Alt="yes" Shift="no" Key="65">
            <Action type="0" message="2453" wParam="0" lParam="0" sParam="" />
            <Action type="1" message="2170" wParam="0" lParam="0" sParam="*" />
            <Action type="1" message="2170" wParam="0" lParam="0" sParam="#" />
            <Action type="1" message="2170" wParam="0" lParam="0" sParam="#" />
            <Action type="1" message="2170" wParam="0" lParam="0" sParam="n" />
            <Action type="1" message="2170" wParam="0" lParam="0" sParam="n" />
            <Action type="1" message="2170" wParam="0" lParam="0" sParam="&#x000D;" />
            <Action type="1" message="2170" wParam="0" lParam="0" sParam="&#x000A;" />
            <Action type="0" message="2452" wParam="0" lParam="0" sParam="" />
            <Action type="0" message="2326" wParam="0" lParam="0" sParam="" />
            <Action type="3" message="1700" wParam="0" lParam="0" sParam="" />
            <Action type="3" message="1601" wParam="0" lParam="0" sParam="^(\*##e)[^\n]*" />
            <Action type="3" message="1625" wParam="0" lParam="2" sParam="" />
            <Action type="3" message="1602" wParam="0" lParam="0" sParam="" />
            <Action type="3" message="1702" wParam="0" lParam="256" sParam="" />
            <Action type="3" message="1701" wParam="0" lParam="1609" sParam="" />
            <Action type="3" message="1700" wParam="0" lParam="0" sParam="" />
            <Action type="3" message="1601" wParam="0" lParam="0" sParam="^(\*##nn)[^\n]*" />
            <Action type="3" message="1625" wParam="0" lParam="2" sParam="" />
            <Action type="3" message="1602" wParam="0" lParam="0" sParam="*##e" />
            <Action type="3" message="1702" wParam="0" lParam="256" sParam="" />
            <Action type="3" message="1701" wParam="0" lParam="1609" sParam="" />
        </Macro>
        <Macro name="Section" Ctrl="yes" Alt="yes" Shift="no" Key="49">
            <Action type="1" message="2170" wParam="0" lParam="0" sParam="/" />
            <Action type="1" message="2170" wParam="0" lParam="0" sParam="*" />
            <Action type="1" message="2170" wParam="0" lParam="0" sParam="=" />
            <Action type="1" message="2170" wParam="0" lParam="0" sParam="=" />
            <Action type="1" message="2170" wParam="0" lParam="0" sParam="=" />
            <Action type="1" message="2170" wParam="0" lParam="0" sParam="=" />
            <Action type="1" message="2170" wParam="0" lParam="0" sParam="=" />
            <Action type="1" message="2170" wParam="0" lParam="0" sParam="=" />
            <Action type="1" message="2170" wParam="0" lParam="0" sParam="=" />
            <Action type="1" message="2170" wParam="0" lParam="0" sParam="=" />
            <Action type="1" message="2170" wParam="0" lParam="0" sParam="=" />
            <Action type="1" message="2170" wParam="0" lParam="0" sParam="=" />
            <Action type="1" message="2170" wParam="0" lParam="0" sParam="=" />
            <Action type="1" message="2170" wParam="0" lParam="0" sParam="=" />
            <Action type="1" message="2170" wParam="0" lParam="0" sParam="=" />
            <Action type="1" message="2170" wParam="0" lParam="0" sParam="=" />
            <Action type="1" message="2170" wParam="0" lParam="0" sParam="=" />
            <Action type="1" message="2170" wParam="0" lParam="0" sParam="=" />
            <Action type="1" message="2170" wParam="0" lParam="0" sParam="=" />
            <Action type="1" message="2170" wParam="0" lParam="0" sParam="=" />
            <Action type="1" message="2170" wParam="0" lParam="0" sParam="=" />
            <Action type="1" message="2170" wParam="0" lParam="0" sParam="=" />
            <Action type="1" message="2170" wParam="0" lParam="0" sParam="=" />
            <Action type="1" message="2170" wParam="0" lParam="0" sParam="=" />
            <Action type="1" message="2170" wParam="0" lParam="0" sParam="=" />
            <Action type="1" message="2170" wParam="0" lParam="0" sParam="=" />
            <Action type="1" message="2170" wParam="0" lParam="0" sParam="=" />
            <Action type="1" message="2170" wParam="0" lParam="0" sParam="=" />
            <Action type="1" message="2170" wParam="0" lParam="0" sParam="=" />
            <Action type="1" message="2170" wParam="0" lParam="0" sParam="=" />
            <Action type="1" message="2170" wParam="0" lParam="0" sParam="=" />
            <Action type="1" message="2170" wParam="0" lParam="0" sParam="=" />
            <Action type="1" message="2170" wParam="0" lParam="0" sParam="=" />
            <Action type="1" message="2170" wParam="0" lParam="0" sParam="=" />
            <Action type="1" message="2170" wParam="0" lParam="0" sParam="=" />
            <Action type="1" message="2170" wParam="0" lParam="0" sParam="=" />
            <Action type="1" message="2170" wParam="0" lParam="0" sParam="=" />
            <Action type="1" message="2170" wParam="0" lParam="0" sParam="=" />
            <Action type="1" message="2170" wParam="0" lParam="0" sParam="=" />
            <Action type="1" message="2170" wParam="0" lParam="0" sParam="=" />
            <Action type="1" message="2170" wParam="0" lParam="0" sParam="=" />
            <Action type="1" message="2170" wParam="0" lParam="0" sParam="=" />
            <Action type="1" message="2170" wParam="0" lParam="0" sParam="=" />
            <Action type="1" message="2170" wParam="0" lParam="0" sParam="=" />
            <Action type="1" message="2170" wParam="0" lParam="0" sParam="=" />
            <Action type="1" message="2170" wParam="0" lParam="0" sParam="=" />
            <Action type="1" message="2170" wParam="0" lParam="0" sParam="=" />
            <Action type="1" message="2170" wParam="0" lParam="0" sParam="=" />
            <Action type="1" message="2170" wParam="0" lParam="0" sParam="=" />
            <Action type="1" message="2170" wParam="0" lParam="0" sParam="=" />
            <Action type="1" message="2170" wParam="0" lParam="0" sParam="=" />
            <Action type="1" message="2170" wParam="0" lParam="0" sParam="=" />
            <Action type="1" message="2170" wParam="0" lParam="0" sParam="&#x000D;" />
            <Action type="1" message="2170" wParam="0" lParam="0" sParam="&#x000A;" />
            <Action type="1" message="2170" wParam="0" lParam="0" sParam=" " />
            <Action type="1" message="2170" wParam="0" lParam="0" sParam=" " />
            <Action type="1" message="2170" wParam="0" lParam="0" sParam=" " />
            <Action type="1" message="2170" wParam="0" lParam="0" sParam=" " />
            <Action type="1" message="2170" wParam="0" lParam="0" sParam=" " />
            <Action type="1" message="2170" wParam="0" lParam="0" sParam=" " />
            <Action type="1" message="2170" wParam="0" lParam="0" sParam=" " />
            <Action type="1" message="2170" wParam="0" lParam="0" sParam=" " />
            <Action type="1" message="2170" wParam="0" lParam="0" sParam=" " />
            <Action type="1" message="2170" wParam="0" lParam="0" sParam=" " />
            <Action type="1" message="2170" wParam="0" lParam="0" sParam=" " />
            <Action type="1" message="2170" wParam="0" lParam="0" sParam="&#x000D;" />
            <Action type="1" message="2170" wParam="0" lParam="0" sParam="&#x000A;" />
            <Action type="1" message="2170" wParam="0" lParam="0" sParam="=" />
            <Action type="1" message="2170" wParam="0" lParam="0" sParam="=" />
            <Action type="1" message="2170" wParam="0" lParam="0" sParam="=" />
            <Action type="1" message="2170" wParam="0" lParam="0" sParam="=" />
            <Action type="1" message="2170" wParam="0" lParam="0" sParam="=" />
            <Action type="1" message="2170" wParam="0" lParam="0" sParam="=" />
            <Action type="1" message="2170" wParam="0" lParam="0" sParam="=" />
            <Action type="1" message="2170" wParam="0" lParam="0" sParam="=" />
            <Action type="1" message="2170" wParam="0" lParam="0" sParam="=" />
            <Action type="1" message="2170" wParam="0" lParam="0" sParam="=" />
            <Action type="1" message="2170" wParam="0" lParam="0" sParam="=" />
            <Action type="1" message="2170" wParam="0" lParam="0" sParam="=" />
            <Action type="1" message="2170" wParam="0" lParam="0" sParam="=" />
            <Action type="1" message="2170" wParam="0" lParam="0" sParam="=" />
            <Action type="1" message="2170" wParam="0" lParam="0" sParam="=" />
            <Action type="1" message="2170" wParam="0" lParam="0" sParam="=" />
            <Action type="1" message="2170" wParam="0" lParam="0" sParam="=" />
            <Action type="1" message="2170" wParam="0" lParam="0" sParam="=" />
            <Action type="1" message="2170" wParam="0" lParam="0" sParam="=" />
            <Action type="1" message="2170" wParam="0" lParam="0" sParam="=" />
            <Action type="1" message="2170" wParam="0" lParam="0" sParam="=" />
            <Action type="1" message="2170" wParam="0" lParam="0" sParam="=" />
            <Action type="1" message="2170" wParam="0" lParam="0" sParam="=" />
            <Action type="1" message="2170" wParam="0" lParam="0" sParam="=" />
            <Action type="1" message="2170" wParam="0" lParam="0" sParam="=" />
            <Action type="1" message="2170" wParam="0" lParam="0" sParam="=" />
            <Action type="1" message="2170" wParam="0" lParam="0" sParam="=" />
            <Action type="1" message="2170" wParam="0" lParam="0" sParam="=" />
            <Action type="1" message="2170" wParam="0" lParam="0" sParam="=" />
            <Action type="1" message="2170" wParam="0" lParam="0" sParam="=" />
            <Action type="1" message="2170" wParam="0" lParam="0" sParam="=" />
            <Action type="1" message="2170" wParam="0" lParam="0" sParam="=" />
            <Action type="1" message="2170" wParam="0" lParam="0" sParam="=" />
            <Action type="1" message="2170" wParam="0" lParam="0" sParam="=" />
            <Action type="1" message="2170" wParam="0" lParam="0" sParam="=" />
            <Action type="1" message="2170" wParam="0" lParam="0" sParam="=" />
            <Action type="1" message="2170" wParam="0" lParam="0" sParam="=" />
            <Action type="1" message="2170" wParam="0" lParam="0" sParam="=" />
            <Action type="1" message="2170" wParam="0" lParam="0" sParam="=" />
            <Action type="1" message="2170" wParam="0" lParam="0" sParam="=" />
            <Action type="1" message="2170" wParam="0" lParam="0" sParam="=" />
            <Action type="1" message="2170" wParam="0" lParam="0" sParam="=" />
            <Action type="1" message="2170" wParam="0" lParam="0" sParam="=" />
            <Action type="1" message="2170" wParam="0" lParam="0" sParam="=" />
            <Action type="1" message="2170" wParam="0" lParam="0" sParam="=" />
            <Action type="1" message="2170" wParam="0" lParam="0" sParam="=" />
            <Action type="1" message="2170" wParam="0" lParam="0" sParam="=" />
            <Action type="1" message="2170" wParam="0" lParam="0" sParam="=" />
            <Action type="1" message="2170" wParam="0" lParam="0" sParam="=" />
            <Action type="1" message="2170" wParam="0" lParam="0" sParam="=" />
            <Action type="1" message="2170" wParam="0" lParam="0" sParam="*" />
            <Action type="1" message="2170" wParam="0" lParam="0" sParam="/" />
        </Macro>
        <Macro name="SubSection" Ctrl="yes" Alt="yes" Shift="no" Key="50">
            <Action type="1" message="2170" wParam="0" lParam="0" sParam="*" />
            <Action type="1" message="2170" wParam="0" lParam="0" sParam="-" />
            <Action type="1" message="2170" wParam="0" lParam="0" sParam="-" />
            <Action type="1" message="2170" wParam="0" lParam="0" sParam="-" />
            <Action type="1" message="2170" wParam="0" lParam="0" sParam="-" />
            <Action type="1" message="2170" wParam="0" lParam="0" sParam="-" />
            <Action type="1" message="2170" wParam="0" lParam="0" sParam="-" />
            <Action type="1" message="2170" wParam="0" lParam="0" sParam="-" />
            <Action type="1" message="2170" wParam="0" lParam="0" sParam="-" />
            <Action type="1" message="2170" wParam="0" lParam="0" sParam="-" />
            <Action type="1" message="2170" wParam="0" lParam="0" sParam="-" />
            <Action type="1" message="2170" wParam="0" lParam="0" sParam=" " />
        </Macro>
    </Macros>
    <UserDefinedCommands>
        <Command name="Launch in Firefox" Ctrl="yes" Alt="yes" Shift="yes" Key="88">firefox &quot;$(FULL_CURRENT_PATH)&quot;</Command>
        <Command name="Launch in IE" Ctrl="yes" Alt="yes" Shift="yes" Key="73">iexplore &quot;$(FULL_CURRENT_PATH)&quot;</Command>
        <Command name="Launch in Chrome" Ctrl="yes" Alt="yes" Shift="yes" Key="82">chrome &quot;$(FULL_CURRENT_PATH)&quot;</Command>
        <Command name="Launch in Safari" Ctrl="yes" Alt="yes" Shift="yes" Key="70">safari &quot;$(FULL_CURRENT_PATH)&quot;</Command>
        <Command name="Get php help" Ctrl="no" Alt="yes" Shift="no" Key="112">http://www.php.net/%20$(CURRENT_WORD)</Command>
        <Command name="Google Search" Ctrl="no" Alt="yes" Shift="no" Key="113">http://www.google.com/search?q=$(CURRENT_WORD)</Command>
        <Command name="Wikipedia Search" Ctrl="no" Alt="yes" Shift="no" Key="114">http://en.wikipedia.org/wiki/Special:Search?search=$(CURRENT_WORD)</Command>
        <Command name="Open file" Ctrl="no" Alt="yes" Shift="no" Key="116">$(NPP_DIRECTORY)\notepad++.exe $(CURRENT_WORD)</Command>
        <Command name="Open in another instance" Ctrl="no" Alt="yes" Shift="no" Key="117">$(NPP_DIRECTORY)\notepad++.exe $(CURRENT_WORD) -nosession -multiInst</Command>
        <Command name="Send via Outlook" Ctrl="yes" Alt="yes" Shift="yes" Key="79">outlook /a &quot;$(FULL_CURRENT_PATH)&quot;</Command>
        <Command name="Run do-lines" Ctrl="no" Alt="no" Shift="no" Key="120">&quot;C:\ado\personal\rundolines.exe&quot;</Command>
        <Command name="Run do-file" Ctrl="no" Alt="no" Shift="no" Key="121">&quot;C:\ado\personal\rundo.exe&quot; &quot;$(FULL_CURRENT_PATH)&quot;</Command>
    </UserDefinedCommands>
    <PluginCommands />
    <ScintillaKeys />
</NotepadPlus>
